clone_latest_weekday_observations.py
clone_observations.py
config.py
export_event_roster.py
import_observations_from_file.py
mage_api.py
mage_python_api-1.0.0.dist-info/LICENSE
mage_python_api-1.0.0.dist-info/METADATA
mage_python_api-1.0.0.dist-info/WHEEL
mage_python_api-1.0.0.dist-info/top_level.txt
mage_python_api-1.0.0.dist-info/RECORD
