Metadata-Version: 2.1
Name: mage-python-api
Version: 1.0.0
Summary: A Python wrapper for the MAGE API.
Author-email: Tesla Government Developers <developers@teslagovernment.com>
License: MIT License        
Project-URL: Homepage, https://github.com/TeslaGov/mage-python-api
Keywords: mobile,awareness,GEOINT,geospatial
Classifier: License :: OSI Approved :: MIT License
Classifier: Programming Language :: Python
Classifier: Programming Language :: Python :: 3
Requires-Python: >=3.10.0
License-File: LICENSE
Requires-Dist: numpy (>=1.23.2)
Requires-Dist: pandas (>=1.4.3)
Requires-Dist: Pillow (>=9.2.0)
Requires-Dist: requests (>=2.28.1)
